py_futuur_client/__init__.py
py_futuur_client/bet.py
py_futuur_client/category.py
py_futuur_client/client.py
py_futuur_client/market.py
py_futuur_client/orders.py
py_futuur_client/user.py
py_futuur_client-1.0.4.dist-info/licenses/LICENCE
py_futuur_client-1.0.4.dist-info/METADATA
py_futuur_client-1.0.4.dist-info/WHEEL
py_futuur_client-1.0.4.dist-info/top_level.txt
py_futuur_client-1.0.4.dist-info/RECORD
