Metadata-Version: 2.4
Name: py-futuur-client
Version: 1.0.4
Summary: A client to interact with Futuur public API.
Home-page: https://github.com/futuur/py_futuur_client.git
Author: Futuur .inc
Author-email: support@futuur.com
License: MIT
Keywords: futuur api client trading prediction-market
Classifier: Development Status :: 3 - Alpha
Classifier: Intended Audience :: Developers
Classifier: Topic :: Software Development :: Libraries :: Python Modules
Classifier: License :: OSI Approved :: MIT License
Classifier: Programming Language :: Python :: 3
Classifier: Programming Language :: Python :: 3.8
Classifier: Programming Language :: Python :: 3.9
Classifier: Programming Language :: Python :: 3.10
Classifier: Programming Language :: Python :: 3.11
Classifier: Operating System :: OS Independent
License-File: LICENCE
Requires-Dist: requests>=2.32.5
Dynamic: author
Dynamic: author-email
Dynamic: classifier
Dynamic: description
Dynamic: description-content-type
Dynamic: home-page
Dynamic: keywords
Dynamic: license
Dynamic: license-file
Dynamic: requires-dist
Dynamic: summary
